perceiver_pytorch/__init__.py
perceiver_pytorch/convolutions.py
perceiver_pytorch/decoders.py
perceiver_pytorch/encoders.py
perceiver_pytorch/gated.py
perceiver_pytorch/layers.py
perceiver_pytorch/mixed_latents.py
perceiver_pytorch/modalities.py
perceiver_pytorch/multi_perceiver_pytorch.py
perceiver_pytorch/perceiver_io.py
perceiver_pytorch/perceiver_pytorch.py
perceiver_pytorch/queries.py
perceiver_pytorch/rotary.py
perceiver_pytorch/utils.py
perceiver_model-0.7.6.dist-info/LICENSE
perceiver_model-0.7.6.dist-info/METADATA
perceiver_model-0.7.6.dist-info/WHEEL
perceiver_model-0.7.6.dist-info/top_level.txt
perceiver_model-0.7.6.dist-info/RECORD
