Metadata-Version: 2.1
Name: perceiver-model
Version: 0.7.6
Summary: Multimodal Perceiver - Pytorch
Home-page: https://github.com/openclimatefix/perceiver-pytorch
Author: Jacob Bieker, Jack Kelly, Peter Dudfield
Author-email: jacob@openclimatefix.org
License: MIT
Keywords: artificial intelligence,deep learning,transformer,attention mechanism
Platform: UNKNOWN
Classifier: Development Status :: 4 - Beta
Classifier: Intended Audience :: Developers
Classifier: Topic :: Scientific/Engineering :: Artificial Intelligence
Classifier: License :: OSI Approved :: MIT License
Classifier: Programming Language :: Python :: 3.6
License-File: LICENSE
Requires-Dist: einops (>=0.3)
Requires-Dist: torch (>=1.6)
Requires-Dist: numpy
Requires-Dist: torchvision
